{
  "_shard": "eu-other",
  "_sources": ["digital-europe", "cef", "life-programme", "erasmus-enterprise", "investeu", "creative-europe", "cerv", "justice-programme", "eu4health", "single-market-programme"],
  "items": [
    { "id": "cef-digital-2026-cabo-submarino", "file": "instrumentos/cef-digital-2026-cabo-submarino.html", "source": "hadea", "state": "aberto", "last_check": "2026-04-10" },
    { "id": "cef-dig-2026-smart-cables", "file": "instrumentos/cef-dig-2026-smart-cables.html", "source": "hadea", "state": "aberto", "last_check": "2026-04-13" },
    { "id": "i3-2026-interregional-innovation-investments", "file": "instrumentos/i3-2026-interregional-innovation-investments.html", "source": "eu-funding-tenders", "state": "previsto", "last_check": "2026-04-13" }
  ]
}
